shona_spacy/__init__.py
shona_spacy/pipeline.py
shona_spacy/shona_component.py
shona_spacy/data/shona_lexicon.json
shona_spacy-0.1.5.dist-info/METADATA
shona_spacy-0.1.5.dist-info/WHEEL
shona_spacy-0.1.5.dist-info/top_level.txt
shona_spacy-0.1.5.dist-info/RECORD
