Metadata-Version: 2.4
Name: shona-spacy
Version: 0.1.5
Summary: A rule-based spaCy pipeline for Shona NLP.
Author-email: Happymore Masoka <happymore@example.com>
License: MIT
Project-URL: Homepage, https://github.com/HappymoreMasoka/shona-spacy
Project-URL: Repository, https://github.com/HappymoreMasoka/shona-spacy
Classifier: Programming Language :: Python :: 3
Classifier: License :: OSI Approved :: MIT License
Classifier: Operating System :: OS Independent
Classifier: Topic :: Scientific/Engineering :: Artificial Intelligence
Classifier: Topic :: Text Processing :: Linguistic
Requires-Python: >=3.8
Requires-Dist: spacy>=3.7
